{
  "pdf_path": "pdfs\\10000835_20251231_194522_AB RD DEC25.pdf",
  "header_zone_detected": [
    {
      "page_no": 0,
      "y_min": 132.73800659179688,
      "y_max": 144.43800354003906,
      "confidence": 0.92,
      "reason": "above_first_data_row_keywords=6"
    },
    {
      "page_no": 1,
      "y_min": 69.73797607421875,
      "y_max": 81.43797302246094,
      "confidence": 0.6,
      "reason": "header_keywords=1 tokens=13"
    },
    {
      "page_no": 2,
      "y_min": 17.23797607421875,
      "y_max": 28.937976837158203,
      "confidence": 0.6,
      "reason": "header_keywords=1 tokens=13"
    },
    {
      "page_no": 3,
      "y_min": 101.23800659179688,
      "y_max": 112.93800354003906,
      "confidence": 0.9,
      "reason": "header_keywords=6 tokens=10"
    },
    {
      "page_no": 4,
      "y_min": 111.73800659179688,
      "y_max": 123.43800354003906,
      "confidence": 0.7,
      "reason": "header_keywords=2 tokens=13"
    },
    {
      "page_no": 5,
      "y_min": 111.73800659179688,
      "y_max": 123.43800354003906,
      "confidence": 0.7,
      "reason": "header_keywords=2 tokens=15"
    },
    {
      "page_no": 6,
      "y_min": 101.23800659179688,
      "y_max": 112.93800354003906,
      "confidence": 0.7,
      "reason": "header_keywords=2 tokens=13"
    },
    {
      "page_no": 7,
      "y_min": 216.73800659179688,
      "y_max": 228.43800354003906,
      "confidence": 0.9,
      "reason": "header_keywords=6 tokens=10"
    },
    {
      "page_no": 8,
      "y_min": 17.23797607421875,
      "y_max": 28.937976837158203,
      "confidence": 0.6,
      "reason": "header_keywords=1 tokens=14"
    },
    {
      "page_no": 9,
      "y_min": 17.23797607421875,
      "y_max": 28.937976837158203,
      "confidence": 0.7,
      "reason": "header_keywords=2 tokens=14"
    },
    {
      "page_no": 10,
      "y_min": 111.73800659179688,
      "y_max": 123.43800354003906,
      "confidence": 0.9,
      "reason": "header_keywords=6 tokens=10"
    },
    {
      "page_no": 11,
      "y_min": 195.73800659179688,
      "y_max": 207.43800354003906,
      "confidence": 0.71,
      "reason": "header_keywords=3 tokens=16"
    },
    {
      "page_no": 12,
      "y_min": 80.23800659179688,
      "y_max": 91.93800354003906,
      "confidence": 0.6,
      "reason": "header_keywords=1 tokens=13"
    },
    {
      "page_no": 13,
      "y_min": 69.73797607421875,
      "y_max": 81.43797302246094,
      "confidence": 0.6,
      "reason": "header_keywords=1 tokens=13"
    },
    {
      "page_no": 14,
      "y_min": 227.23800659179688,
      "y_max": 238.93800354003906,
      "confidence": 0.9,
      "reason": "header_keywords=6 tokens=10"
    },
    {
      "page_no": 15,
      "y_min": 90.73800659179688,
      "y_max": 102.43800354003906,
      "confidence": 0.6,
      "reason": "header_keywords=1 tokens=15"
    },
    {
      "page_no": 16,
      "y_min": 17.23797607421875,
      "y_max": 28.937976837158203,
      "confidence": 0.6,
      "reason": "header_keywords=1 tokens=14"
    },
    {
      "page_no": 17,
      "y_min": 122.23800659179688,
      "y_max": 133.93800354003906,
      "confidence": 0.9,
      "reason": "header_keywords=6 tokens=10"
    },
    {
      "page_no": 18,
      "y_min": 216.73800659179688,
      "y_max": 228.43800354003906,
      "confidence": 0.7,
      "reason": "header_keywords=2 tokens=14"
    },
    {
      "page_no": 19,
      "y_min": 269.2380065917969,
      "y_max": 280.9380187988281,
      "confidence": 0.7,
      "reason": "header_keywords=2 tokens=14"
    },
    {
      "page_no": 20,
      "y_min": 17.23797607421875,
      "y_max": 28.937976837158203,
      "confidence": 0.92,
      "reason": "above_first_data_row_keywords=6"
    },
    {
      "page_no": 21,
      "y_min": 17.23797607421875,
      "y_max": 28.937976837158203,
      "confidence": 0.5,
      "reason": "largest_font_top"
    }
  ],
  "raw_header_candidates": null,
  "final_selected_header": null,
  "confidence": 0.0,
  "confidence_breakdown": {},
  "debug": {
    "reason": "no_header_candidates",
    "candidate_header_rows": [
      {
        "page_no": 0,
        "headers": [
          "Stock",
          "Purchase",
          "Purchase",
          "RETURN",
          "RETURN",
          "OTHERS",
          "OTHERS",
          "Stock",
          "Stock",
          "Sales",
          "RETURN",
          "RETURN",
          "OTHERS",
          "OTHERS",
          "Stock",
          "Stock",
          "Rate"
        ],
        "data_column_count_detected": 11,
        "combined_confidence": 0.8066705882352941
      },
      {
        "page_no": 1,
        "headers": [
          "ANASPAS",
          "ING",
          "2Ml",
          "25.67"
        ],
        "data_column_count_detected": 12,
        "combined_confidence": 0.7112964285714286
      },
      {
        "page_no": 2,
        "headers": [
          "BETONIN",
          "200Ml",
          "200Ml",
          "113.65"
        ],
        "data_column_count_detected": 12,
        "combined_confidence": 0.7099676470588236
      },
      {
        "page_no": 3,
        "headers": [
          "Stock",
          "Stock",
          "Purchase",
          "Purchase",
          "RETURN",
          "OTHERS",
          "OTHERS",
          "Stock",
          "Stock",
          "Sales",
          "Sales",
          "RETURN",
          "RETURN",
          "OTHERS",
          "OTHERS",
          "Stock",
          "Stock",
          "Rate"
        ],
        "data_column_count_detected": 12,
        "combined_confidence": 0.8062222222222223
      },
      {
        "page_no": 4,
        "headers": [
          "DURAJOINT",
          "PRO",
          "10'S",
          "0.00"
        ],
        "data_column_count_detected": 12,
        "combined_confidence": 0.7350461538461538
      },
      {
        "page_no": 5,
        "headers": [
          "ERTYCIN",
          "TAB",
          "6'S",
          "58.22"
        ],
        "data_column_count_detected": 12,
        "combined_confidence": 0.748295652173913
      },
      {
        "page_no": 6,
        "headers": [
          "Cl",
          "AT",
          "15Gm",
          "224.87"
        ],
        "data_column_count_detected": 12,
        "combined_confidence": 0.7535285714285714
      },
      {
        "page_no": 7,
        "headers": [
          "Stock",
          "Stock",
          "Purchase",
          "Purchase",
          "RETURN",
          "RETURN",
          "OTHERS",
          "OTHERS",
          "Stock",
          "Stock",
          "Sales",
          "Sales",
          "RETURN",
          "RETURN",
          "OTHERS",
          "OTHERS",
          "Stock",
          "Stock",
          "Rate"
        ],
        "data_column_count_detected": 13,
        "combined_confidence": 0.801621052631579
      },
      {
        "page_no": 8,
        "headers": [
          "GLUFORMIN",
          "XL",
          "1000Mg",
          "10'S",
          "26.88"
        ],
        "data_column_count_detected": 13,
        "combined_confidence": 0.7154436363636364
      },
      {
        "page_no": 9,
        "headers": [
          "KENACORT",
          "40Mg",
          "ING",
          "1Ml",
          "145.41"
        ],
        "data_column_count_detected": 12,
        "combined_confidence": 0.7353768421052632
      },
      {
        "page_no": 10,
        "headers": [
          "Stock",
          "Stock",
          "Purchase",
          "Purchase",
          "RETURN",
          "RETURN",
          "OTHERS",
          "OTHERS",
          "Stock",
          "Sales",
          "Sales",
          "RETURN",
          "RETURN",
          "OTHERS",
          "OTHERS",
          "Stock",
          "Stock",
          "Rate"
        ],
        "data_column_count_detected": 12,
        "combined_confidence": 0.8017777777777778
      },
      {
        "page_no": 11,
        "headers": [
          "MINICHEK",
          "Quantity",
          "HAIR",
          "LOSS",
          "100Ml",
          "356.34"
        ],
        "data_column_count_detected": 12,
        "combined_confidence": 0.7356971014492755
      },
      {
        "page_no": 12,
        "headers": [
          "NERVUP",
          "ER",
          "10'S",
          "124.01"
        ],
        "data_column_count_detected": 12,
        "combined_confidence": 0.714023076923077
      },
      {
        "page_no": 13,
        "headers": [
          "ORAHEX",
          "PRO",
          "150;Ml",
          "199.52"
        ],
        "data_column_count_detected": 13,
        "combined_confidence": 0.7099846153846154
      },
      {
        "page_no": 14,
        "headers": [
          "Stock",
          "Stock",
          "Purchase",
          "Purchase",
          "RETURN",
          "RETURN",
          "OTHERS",
          "OTHERS",
          "Stock",
          "Stock",
          "Sales",
          "Sales",
          "RETURN",
          "RETURN",
          "OTHERS",
          "OTHERS",
          "Stock",
          "Stock",
          "Rate"
        ],
        "data_column_count_detected": 12,
        "combined_confidence": 0.8016342105263159
      },
      {
        "page_no": 15,
        "headers": [
          "ROCKBON",
          "TAB",
          "10'S",
          "41.58"
        ],
        "data_column_count_detected": 12,
        "combined_confidence": 0.7229333333333334
      },
      {
        "page_no": 16,
        "headers": [
          "SOLSPRE",
          "SPRAY",
          "100Ml",
          "358.47"
        ],
        "data_column_count_detected": 11,
        "combined_confidence": 0.7157038961038962
      },
      {
        "page_no": 17,
        "headers": [
          "Stock",
          "Stock",
          "Purchase",
          "Purchase",
          "RETURN",
          "RETURN",
          "OTHERS",
          "OTHERS",
          "Stock",
          "Sales",
          "RETURN",
          "RETURN",
          "OTHERS",
          "OTHERS",
          "Stock",
          "Stock",
          "Rate"
        ],
        "data_column_count_detected": 12,
        "combined_confidence": 0.8017558823529412
      },
      {
        "page_no": 18,
        "headers": [
          "Op",
          "IM",
          "ING",
          "3Ml",
          "5.20"
        ],
        "data_column_count_detected": 11,
        "combined_confidence": 0.7486682352941176
      },
      {
        "page_no": 19,
        "headers": [
          "VALACE",
          "OD",
          "1000Mg",
          "15'S",
          "194.29"
        ],
        "data_column_count_detected": 11,
        "combined_confidence": 0.7400800000000001
      },
      {
        "page_no": 20,
        "headers": [
          "Stock",
          "Stock",
          "Purchase",
          "Purchase",
          "RETURN",
          "RETURN",
          "OTHERS",
          "OTHERS",
          "Stock",
          "Sales",
          "Sales",
          "RETURN",
          "RETURN",
          "OTHERS",
          "OTHERS",
          "Stock",
          "Stock",
          "Rate"
        ],
        "data_column_count_detected": 12,
        "combined_confidence": 0.8065111111111112
      },
      {
        "page_no": 21,
        "headers": [
          "ZOMELIS",
          "50Mg",
          "10'S",
          "200.91"
        ],
        "data_column_count_detected": 11,
        "combined_confidence": 0.6873125
      }
    ],
    "rejected_candidates_reason": [
      {
        "page_no": 0,
        "reason": "column_count_mismatch: header=17 data=11 diff=6",
        "evidence_debug": {
          "column_count_gate": {
            "passed": false,
            "reason": "column_count_mismatch: header=17 data=11 diff=6"
          }
        }
      },
      {
        "page_no": 1,
        "reason": "column_count_mismatch: header=4 data=12 diff=8",
        "evidence_debug": {
          "column_count_gate": {
            "passed": false,
            "reason": "column_count_mismatch: header=4 data=12 diff=8"
          }
        }
      },
      {
        "page_no": 2,
        "reason": "column_count_mismatch: header=4 data=12 diff=8",
        "evidence_debug": {
          "column_count_gate": {
            "passed": false,
            "reason": "column_count_mismatch: header=4 data=12 diff=8"
          }
        }
      },
      {
        "page_no": 3,
        "reason": "column_count_mismatch: header=18 data=12 diff=6",
        "evidence_debug": {
          "column_count_gate": {
            "passed": false,
            "reason": "column_count_mismatch: header=18 data=12 diff=6"
          }
        }
      },
      {
        "page_no": 4,
        "reason": "column_count_mismatch: header=4 data=12 diff=8",
        "evidence_debug": {
          "column_count_gate": {
            "passed": false,
            "reason": "column_count_mismatch: header=4 data=12 diff=8"
          }
        }
      },
      {
        "page_no": 5,
        "reason": "column_count_mismatch: header=4 data=12 diff=8",
        "evidence_debug": {
          "column_count_gate": {
            "passed": false,
            "reason": "column_count_mismatch: header=4 data=12 diff=8"
          }
        }
      },
      {
        "page_no": 6,
        "reason": "column_count_mismatch: header=4 data=12 diff=8",
        "evidence_debug": {
          "column_count_gate": {
            "passed": false,
            "reason": "column_count_mismatch: header=4 data=12 diff=8"
          }
        }
      },
      {
        "page_no": 7,
        "reason": "column_count_mismatch: header=19 data=13 diff=6",
        "evidence_debug": {
          "column_count_gate": {
            "passed": false,
            "reason": "column_count_mismatch: header=19 data=13 diff=6"
          }
        }
      },
      {
        "page_no": 8,
        "reason": "column_count_mismatch: header=5 data=13 diff=8",
        "evidence_debug": {
          "column_count_gate": {
            "passed": false,
            "reason": "column_count_mismatch: header=5 data=13 diff=8"
          }
        }
      },
      {
        "page_no": 9,
        "reason": "column_count_mismatch: header=5 data=12 diff=7",
        "evidence_debug": {
          "column_count_gate": {
            "passed": false,
            "reason": "column_count_mismatch: header=5 data=12 diff=7"
          }
        }
      },
      {
        "page_no": 10,
        "reason": "column_count_mismatch: header=18 data=12 diff=6",
        "evidence_debug": {
          "column_count_gate": {
            "passed": false,
            "reason": "column_count_mismatch: header=18 data=12 diff=6"
          }
        }
      },
      {
        "page_no": 11,
        "reason": "column_count_mismatch: header=6 data=12 diff=6",
        "evidence_debug": {
          "column_count_gate": {
            "passed": false,
            "reason": "column_count_mismatch: header=6 data=12 diff=6"
          }
        }
      },
      {
        "page_no": 12,
        "reason": "column_count_mismatch: header=4 data=12 diff=8",
        "evidence_debug": {
          "column_count_gate": {
            "passed": false,
            "reason": "column_count_mismatch: header=4 data=12 diff=8"
          }
        }
      },
      {
        "page_no": 13,
        "reason": "column_count_mismatch: header=4 data=13 diff=9",
        "evidence_debug": {
          "column_count_gate": {
            "passed": false,
            "reason": "column_count_mismatch: header=4 data=13 diff=9"
          }
        }
      },
      {
        "page_no": 14,
        "reason": "column_count_mismatch: header=19 data=12 diff=7",
        "evidence_debug": {
          "column_count_gate": {
            "passed": false,
            "reason": "column_count_mismatch: header=19 data=12 diff=7"
          }
        }
      },
      {
        "page_no": 15,
        "reason": "column_count_mismatch: header=4 data=12 diff=8",
        "evidence_debug": {
          "column_count_gate": {
            "passed": false,
            "reason": "column_count_mismatch: header=4 data=12 diff=8"
          }
        }
      },
      {
        "page_no": 16,
        "reason": "column_count_mismatch: header=4 data=11 diff=7",
        "evidence_debug": {
          "column_count_gate": {
            "passed": false,
            "reason": "column_count_mismatch: header=4 data=11 diff=7"
          }
        }
      },
      {
        "page_no": 17,
        "reason": "column_count_mismatch: header=17 data=12 diff=5",
        "evidence_debug": {
          "column_count_gate": {
            "passed": false,
            "reason": "column_count_mismatch: header=17 data=12 diff=5"
          }
        }
      },
      {
        "page_no": 18,
        "reason": "column_count_mismatch: header=5 data=11 diff=6",
        "evidence_debug": {
          "column_count_gate": {
            "passed": false,
            "reason": "column_count_mismatch: header=5 data=11 diff=6"
          }
        }
      },
      {
        "page_no": 19,
        "reason": "column_count_mismatch: header=5 data=11 diff=6",
        "evidence_debug": {
          "column_count_gate": {
            "passed": false,
            "reason": "column_count_mismatch: header=5 data=11 diff=6"
          }
        }
      },
      {
        "page_no": 20,
        "reason": "column_count_mismatch: header=18 data=12 diff=6",
        "evidence_debug": {
          "column_count_gate": {
            "passed": false,
            "reason": "column_count_mismatch: header=18 data=12 diff=6"
          }
        }
      },
      {
        "page_no": 21,
        "reason": "column_count_mismatch: header=4 data=11 diff=7",
        "evidence_debug": {
          "column_count_gate": {
            "passed": false,
            "reason": "column_count_mismatch: header=4 data=11 diff=7"
          }
        }
      }
    ]
  }
}