{
  "pdf_path": "pdfs\\10013188_20260109_184815_SOLVAY.PDF",
  "header_zone_detected": [
    {
      "page_no": 0,
      "y_min": 256.51953125,
      "y_max": 272.52752685546875,
      "confidence": 0.92,
      "reason": "above_first_data_row_keywords=4"
    }
  ],
  "raw_header_candidates": [
    {
      "page_no": 0,
      "headers": [
        "SNO.",
        "PARTICULARS",
        "Pack",
        "Quantity",
        "CASE",
        "Rate",
        "Amount"
      ],
      "combined_confidence": 0.6583999999999999,
      "visual_score": 0.92,
      "reconstruction_score": 0.84,
      "semantic_score": 0.8142857142857143,
      "data_validation_score": 0.7777142857142857,
      "data_column_count_detected": 7
    }
  ],
  "final_selected_header": [
    "SNO.",
    "PARTICULARS",
    "Pack",
    "Quantity",
    "CASE",
    "Rate",
    "Amount"
  ],
  "confidence": 0.6583999999999999,
  "confidence_breakdown": {
    "visual_score": 0.92,
    "reconstruction_score": 0.84,
    "semantic_score": 0.8142857142857143,
    "data_validation_score": 0.7777142857142857,
    "consensus_score": 1.0
  },
  "debug": {
    "reconstructed": [
      "SNO.",
      "PARTICULARS",
      "PACKING",
      "QTY+FREE",
      "CASE",
      "RATE",
      "AMOUNT"
    ],
    "normalized": [
      "SNO.",
      "PARTICULARS",
      "Pack",
      "Quantity",
      "CASE",
      "Rate",
      "Amount"
    ],
    "merge_operations_performed": [],
    "split_operations_performed": [],
    "noise_tokens_removed": [],
    "data_column_count_detected": 7,
    "precision_evidence": {
      "column_count_gate": {
        "passed": true,
        "reason": "column_count_ok: header=7 data=7"
      },
      "penalty_breakdown": {
        "data_type_mismatch_penalty": 0.2
      },
      "adjusted_confidence": 0.6583999999999999,
      "evidence_scores": {
        "keyword_score": 0.5714285714285714,
        "column_alignment_score": 1.0,
        "data_validation_score": 0.7777142857142857,
        "lexical_purity_score": 1.0,
        "multi_page_presence_score": 1.0
      },
      "evidence_total": 0.8372857142857143,
      "evidence_before_penalties": 0.8372857142857143
    },
    "candidate_header_rows": [
      {
        "page_no": 0,
        "headers": [
          "SNO.",
          "PARTICULARS",
          "Pack",
          "Quantity",
          "CASE",
          "Rate",
          "Amount"
        ],
        "data_column_count_detected": 7,
        "combined_confidence": 0.8583999999999999
      }
    ],
    "rejected_candidates_reason": [],
    "final_header_columns": [
      "SNO.",
      "PARTICULARS",
      "Pack",
      "Quantity",
      "CASE",
      "Rate",
      "Amount"
    ]
  }
}