{
  "pdf_path": "pdfs\\10011639_20260102_130338_REPORT_7D40RXKEJ.PDF",
  "header_zone_detected": [
    {
      "page_no": 0,
      "y_min": 133.21798706054688,
      "y_max": 141.0179901123047,
      "confidence": 0.92,
      "reason": "above_first_data_row_keywords=13"
    },
    {
      "page_no": 1,
      "y_min": 17.718017578125,
      "y_max": 25.518016815185547,
      "confidence": 0.5,
      "reason": "largest_font_top"
    }
  ],
  "raw_header_candidates": [
    {
      "page_no": 0,
      "headers": [
        "Product Name",
        "Description",
        "Op",
        "Sales",
        "Sale",
        "Sales",
        "Sales",
        "Purchase",
        "Purchase",
        "Purchase",
        "Purchase",
        "Other",
        "Closing",
        "Closing",
        "Expiry Date",
        "Expiry Date"
      ],
      "combined_confidence": 0.460157327231592,
      "visual_score": 0.92,
      "reconstruction_score": 1.0,
      "semantic_score": 0.934375,
      "data_validation_score": 0.7164116361579597,
      "data_column_count_detected": 16
    }
  ],
  "final_selected_header": [
    "Product Name",
    "Description",
    "Op",
    "Sales",
    "Sale",
    "Sales",
    "Sales",
    "Purchase",
    "Purchase",
    "Purchase",
    "Purchase",
    "Other",
    "Closing",
    "Closing",
    "Expiry Date",
    "Expiry Date"
  ],
  "confidence": 0.460157327231592,
  "confidence_breakdown": {
    "visual_score": 0.92,
    "reconstruction_score": 1.0,
    "semantic_score": 0.934375,
    "data_validation_score": 0.7164116361579597,
    "consensus_score": 0.5
  },
  "debug": {
    "reconstructed": [
      "Item",
      "Description",
      "Opening",
      "Sales",
      "Sale",
      "Sales",
      "Sales",
      "Purchase",
      "Purchase",
      "Purchase",
      "Purchase",
      "Other",
      "Closing",
      "Closing",
      "Expiry",
      "Expiry"
    ],
    "normalized": [
      "Product Name",
      "Description",
      "Op",
      "Sales",
      "Sale",
      "Sales",
      "Sales",
      "Purchase",
      "Purchase",
      "Purchase",
      "Purchase",
      "Other",
      "Closing",
      "Closing",
      "Expiry Date",
      "Expiry Date"
    ],
    "merge_operations_performed": [],
    "split_operations_performed": [],
    "noise_tokens_removed": [],
    "data_column_count_detected": 16,
    "precision_evidence": {
      "column_count_gate": {
        "passed": true,
        "reason": "column_count_ok: header=16 data=16"
      },
      "penalty_breakdown": {
        "data_type_mismatch_penalty": 0.4
      },
      "adjusted_confidence": 0.460157327231592,
      "evidence_scores": {
        "keyword_score": 0.7894736842105263,
        "column_alignment_score": 1.0,
        "data_validation_score": 0.7164116361579597,
        "lexical_purity_score": 1.0,
        "multi_page_presence_score": 0.5
      },
      "evidence_total": 0.8264713300921216,
      "evidence_before_penalties": 0.8264713300921216
    },
    "candidate_header_rows": [
      {
        "page_no": 0,
        "headers": [
          "Product Name",
          "Description",
          "Op",
          "Sales",
          "Sale",
          "Sales",
          "Sales",
          "Purchase",
          "Purchase",
          "Purchase",
          "Purchase",
          "Other",
          "Closing",
          "Closing",
          "Expiry Date",
          "Expiry Date"
        ],
        "data_column_count_detected": 16,
        "combined_confidence": 0.860157327231592
      },
      {
        "page_no": 1,
        "headers": [
          "ABBOTT",
          "HEALTHCARE",
          "PVT",
          "LTD,PATN",
          "36722.00"
        ],
        "data_column_count_detected": 7,
        "combined_confidence": 0.6570329670329671
      }
    ],
    "rejected_candidates_reason": [
      {
        "page_no": 1,
        "reason": "column_count_mismatch: header=5 data=7 diff=2",
        "evidence_debug": {
          "column_count_gate": {
            "passed": false,
            "reason": "column_count_mismatch: header=5 data=7 diff=2"
          }
        }
      }
    ],
    "final_header_columns": [
      "Product Name",
      "Description",
      "Op",
      "Sales",
      "Sale",
      "Sales",
      "Sales",
      "Purchase",
      "Purchase",
      "Purchase",
      "Purchase",
      "Other",
      "Closing",
      "Closing",
      "Expiry Date",
      "Expiry Date"
    ]
  }
}