{
  "pdf_path": "pdfs\\10035103_20260101_132543_NAIL_SalesAndStockStatement.pdf",
  "header_zone_detected": [
    {
      "page_no": 0,
      "y_min": 163.8088836669922,
      "y_max": 175.8148956298828,
      "confidence": 0.92,
      "reason": "above_first_data_row_keywords=14"
    },
    {
      "page_no": 1,
      "y_min": 104.8482894897461,
      "y_max": 116.85428619384766,
      "confidence": 0.92,
      "reason": "above_first_data_row_keywords=14"
    },
    {
      "page_no": 2,
      "y_min": 104.8482894897461,
      "y_max": 116.85428619384766,
      "confidence": 0.92,
      "reason": "above_first_data_row_keywords=14"
    },
    {
      "page_no": 3,
      "y_min": 45.60417938232422,
      "y_max": 57.61017608642578,
      "confidence": 0.6,
      "reason": "header_keywords=1 tokens=9"
    }
  ],
  "raw_header_candidates": [
    {
      "page_no": 0,
      "headers": [
        "Product Code",
        "Product Name",
        "Pack",
        "Op",
        "Op",
        "Bal",
        "Receipt",
        "Purchase",
        "Tot",
        "Issue",
        "Sale",
        "Shortage",
        "Shortage",
        "Expiry Date",
        "Expiry Date",
        "Closing",
        "Closing",
        "Bala"
      ],
      "combined_confidence": 0.13388888888888884,
      "visual_score": 0.92,
      "reconstruction_score": 1.0,
      "semantic_score": 0.8527777777777777,
      "data_validation_score": 0.6666666666666666,
      "data_column_count_detected": 17
    },
    {
      "page_no": 3,
      "headers": [
        "GRAND",
        "Tot",
        "788784.50",
        "197031.80",
        "289021.20",
        "0.00",
        "665630.71"
      ],
      "combined_confidence": 0.35000000000000003,
      "visual_score": 0.6,
      "reconstruction_score": 0.8799999999999999,
      "semantic_score": 0.65,
      "data_validation_score": 0.5,
      "data_column_count_detected": 0
    }
  ],
  "final_selected_header": [
    "GRAND",
    "Tot",
    "788784.50",
    "197031.80",
    "289021.20",
    "0.00",
    "665630.71"
  ],
  "confidence": 0.35000000000000003,
  "confidence_breakdown": {
    "visual_score": 0.6,
    "reconstruction_score": 0.8799999999999999,
    "semantic_score": 0.65,
    "data_validation_score": 0.5,
    "consensus_score": 0.5
  },
  "debug": {
    "reconstructed": [
      "GRAND",
      "TOTAL",
      "788784.50",
      "197031.80",
      "289021.20",
      "0.00",
      "665630.71"
    ],
    "normalized": [
      "GRAND",
      "Tot",
      "788784.50",
      "197031.80",
      "289021.20",
      "0.00",
      "665630.71"
    ],
    "merge_operations_performed": [],
    "split_operations_performed": [],
    "noise_tokens_removed": [
      "0",
      "16"
    ],
    "data_column_count_detected": 17,
    "precision_evidence": {
      "column_count_gate": {
        "passed": true,
        "reason": "no_data_to_compare"
      },
      "penalty_breakdown": {
        "noise_word_penalty": 0.3
      },
      "adjusted_confidence": 0.35000000000000003,
      "evidence_scores": {
        "keyword_score": 0.14285714285714285,
        "column_alignment_score": 0.5,
        "data_validation_score": 0.5,
        "lexical_purity_score": 0.76,
        "multi_page_presence_score": 0.25
      },
      "evidence_total": 0.4247142857142857,
      "evidence_before_penalties": 0.4247142857142857
    },
    "candidate_header_rows": [
      {
        "page_no": 0,
        "headers": [
          "Product Code",
          "Product Name",
          "Pack",
          "Op",
          "Op",
          "Bal",
          "Receipt",
          "Purchase",
          "Tot",
          "Issue",
          "Sale",
          "Shortage",
          "Shortage",
          "Expiry Date",
          "Expiry Date",
          "Closing",
          "Closing",
          "Bala"
        ],
        "data_column_count_detected": 17,
        "combined_confidence": 0.8338888888888889
      },
      {
        "page_no": 1,
        "headers": [
          "Product Code",
          "Product Name",
          "Pack",
          "Op",
          "Op",
          "Bal",
          "Receipt",
          "Purchase",
          "Tot",
          "Issue",
          "Sale",
          "Shortage",
          "Shortage",
          "Expiry Date",
          "Expiry Date",
          "Closing",
          "Closing",
          "Bala"
        ],
        "data_column_count_detected": 16,
        "combined_confidence": 0.8485555555555556
      },
      {
        "page_no": 2,
        "headers": [
          "Product Code",
          "Product Name",
          "Pack",
          "Op",
          "Op",
          "Bal",
          "Receipt",
          "Purchase",
          "Tot",
          "Issue",
          "Sale",
          "Shortage",
          "Shortage",
          "Expiry Date",
          "Expiry Date",
          "Closing",
          "Closing",
          "Bala"
        ],
        "data_column_count_detected": 4,
        "combined_confidence": 0.8198282828282829
      },
      {
        "page_no": 3,
        "headers": [
          "GRAND",
          "Tot",
          "788784.50",
          "197031.80",
          "289021.20",
          "0.00",
          "665630.71"
        ],
        "data_column_count_detected": 0,
        "combined_confidence": 0.65
      }
    ],
    "rejected_candidates_reason": [
      {
        "page_no": 1,
        "reason": "column_count_mismatch: header=18 data=16 diff=2",
        "evidence_debug": {
          "column_count_gate": {
            "passed": false,
            "reason": "column_count_mismatch: header=18 data=16 diff=2"
          }
        }
      },
      {
        "page_no": 2,
        "reason": "column_count_mismatch: header=18 data=4 diff=14",
        "evidence_debug": {
          "column_count_gate": {
            "passed": false,
            "reason": "column_count_mismatch: header=18 data=4 diff=14"
          }
        }
      }
    ],
    "final_header_columns": [
      "GRAND",
      "Tot",
      "788784.50",
      "197031.80",
      "289021.20",
      "0.00",
      "665630.71"
    ]
  }
}