{
  "pdf_path": "pdfs\\10033031_20260101_160243_ABBOTTINDIA.PDF",
  "header_zone_detected": [
    {
      "page_no": 0,
      "y_min": 249.59548950195312,
      "y_max": 258.9335021972656,
      "confidence": 0.92,
      "reason": "above_first_data_row_keywords=7"
    },
    {
      "page_no": 1,
      "y_min": 196.87112426757812,
      "y_max": 206.20912170410156,
      "confidence": 0.92,
      "reason": "above_first_data_row_keywords=7"
    },
    {
      "page_no": 2,
      "y_min": 196.87112426757812,
      "y_max": 206.20912170410156,
      "confidence": 0.92,
      "reason": "above_first_data_row_keywords=7"
    },
    {
      "page_no": 3,
      "y_min": 196.87112426757812,
      "y_max": 206.20912170410156,
      "confidence": 0.92,
      "reason": "above_first_data_row_keywords=7"
    },
    {
      "page_no": 4,
      "y_min": 196.87112426757812,
      "y_max": 206.20912170410156,
      "confidence": 0.92,
      "reason": "above_first_data_row_keywords=7"
    },
    {
      "page_no": 5,
      "y_min": 196.87112426757812,
      "y_max": 206.20912170410156,
      "confidence": 0.92,
      "reason": "above_first_data_row_keywords=7"
    }
  ],
  "raw_header_candidates": null,
  "final_selected_header": null,
  "confidence": 0.0,
  "confidence_breakdown": {},
  "debug": {
    "reason": "no_header_candidates",
    "candidate_header_rows": [
      {
        "page_no": 0,
        "headers": [
          "Quantity",
          "Quantity",
          "Quantity",
          "Quantity",
          "Quantity",
          "Quantity",
          "Quantity",
          "Quantity",
          "Quantity",
          "Quantity",
          "Quantity",
          "Balance",
          "Balance",
          "Quantity",
          "Quantity",
          "Rate"
        ],
        "data_column_count_detected": 11,
        "combined_confidence": 0.835765625
      },
      {
        "page_no": 1,
        "headers": [
          "Quantity",
          "Quantity",
          "Quantity",
          "Quantity",
          "Quantity",
          "Quantity",
          "Quantity",
          "Quantity",
          "Quantity",
          "Quantity",
          "Quantity",
          "Quantity",
          "Balance",
          "Balance",
          "Quantity",
          "Quantity",
          "Rate"
        ],
        "data_column_count_detected": 11,
        "combined_confidence": 0.8334671280276816
      },
      {
        "page_no": 2,
        "headers": [
          "Quantity",
          "Quantity",
          "Quantity",
          "Quantity",
          "Quantity",
          "Quantity",
          "Quantity",
          "Quantity",
          "Quantity",
          "Quantity",
          "Quantity",
          "Quantity",
          "Balance",
          "Quantity",
          "Quantity",
          "Rate"
        ],
        "data_column_count_detected": 11,
        "combined_confidence": 0.8410000000000001
      },
      {
        "page_no": 3,
        "headers": [
          "Quantity",
          "Quantity",
          "Quantity",
          "Quantity",
          "Quantity",
          "Quantity",
          "Quantity",
          "Quantity",
          "Quantity",
          "Quantity",
          "Balance",
          "Balance",
          "Quantity",
          "Quantity",
          "Rate"
        ],
        "data_column_count_detected": 11,
        "combined_confidence": 0.837247619047619
      },
      {
        "page_no": 4,
        "headers": [
          "Quantity",
          "Quantity",
          "Quantity",
          "Quantity",
          "Quantity",
          "Quantity",
          "Quantity",
          "Quantity",
          "Quantity",
          "Quantity",
          "Balance",
          "Balance",
          "Quantity",
          "Quantity",
          "Rate"
        ],
        "data_column_count_detected": 11,
        "combined_confidence": 0.8378666666666668
      },
      {
        "page_no": 5,
        "headers": [
          "Quantity",
          "Quantity",
          "Quantity",
          "Quantity",
          "Quantity",
          "Quantity",
          "Quantity",
          "Quantity",
          "Quantity",
          "Quantity",
          "Quantity",
          "Quantity",
          "Balance",
          "Quantity",
          "Rate"
        ],
        "data_column_count_detected": 11,
        "combined_confidence": 0.8437333333333333
      }
    ],
    "rejected_candidates_reason": [
      {
        "page_no": 0,
        "reason": "column_count_mismatch: header=16 data=11 diff=5",
        "evidence_debug": {
          "column_count_gate": {
            "passed": false,
            "reason": "column_count_mismatch: header=16 data=11 diff=5"
          }
        }
      },
      {
        "page_no": 1,
        "reason": "column_count_mismatch: header=17 data=11 diff=6",
        "evidence_debug": {
          "column_count_gate": {
            "passed": false,
            "reason": "column_count_mismatch: header=17 data=11 diff=6"
          }
        }
      },
      {
        "page_no": 2,
        "reason": "column_count_mismatch: header=16 data=11 diff=5",
        "evidence_debug": {
          "column_count_gate": {
            "passed": false,
            "reason": "column_count_mismatch: header=16 data=11 diff=5"
          }
        }
      },
      {
        "page_no": 3,
        "reason": "column_count_mismatch: header=15 data=11 diff=4",
        "evidence_debug": {
          "column_count_gate": {
            "passed": false,
            "reason": "column_count_mismatch: header=15 data=11 diff=4"
          }
        }
      },
      {
        "page_no": 4,
        "reason": "column_count_mismatch: header=15 data=11 diff=4",
        "evidence_debug": {
          "column_count_gate": {
            "passed": false,
            "reason": "column_count_mismatch: header=15 data=11 diff=4"
          }
        }
      },
      {
        "page_no": 5,
        "reason": "column_count_mismatch: header=15 data=11 diff=4",
        "evidence_debug": {
          "column_count_gate": {
            "passed": false,
            "reason": "column_count_mismatch: header=15 data=11 diff=4"
          }
        }
      }
    ]
  }
}